physicool/__init__.py
physicool/config.py
physicool/datatypes.py
physicool/optimization.py
physicool/pcxml.py
physicool/plotting.py
physicool/processing.py
physicool/updaters.py
physicool-0.2.4.dist-info/LICENSE
physicool-0.2.4.dist-info/WHEEL
physicool-0.2.4.dist-info/METADATA
physicool-0.2.4.dist-info/RECORD
