Metadata-Version: 2.1
Name: physicool
Version: 0.2.4
Summary: A generalized, model-agnostic framework for model calibration in PhysiCell.
License: BSD-3-Clause
Author: Inês Gonçalves, David Hormuth, Caleb Phillips, Sandhya Prabhakaran
Requires-Python: >=3.8,<4.0
Classifier: License :: OSI Approved :: BSD License
Classifier: Programming Language :: Python :: 3
Classifier: Programming Language :: Python :: 3.10
Classifier: Programming Language :: Python :: 3.8
Classifier: Programming Language :: Python :: 3.9
Requires-Dist: matplotlib (>=3.5.1,<4.0.0)
Requires-Dist: numpy (>=1.22.2,<2.0.0)
Requires-Dist: pandas (>=1.4.1,<2.0.0)
Requires-Dist: pydantic (>=1.9.1,<2.0.0)
Requires-Dist: scipy (>=1.8.0,<2.0.0)
